clouderizer/.aws-sam/build.toml
clouderizer/LICENSE
clouderizer/README
clouderizer/__init__.py
clouderizer/cldz_aws_lambda.py
clouderizer/cldz_cli.py
clouderizer/dockerfiles/AutomlDockerfile
clouderizer/dockerfiles/PythonDockerfile
clouderizer/globals.py
clouderizer/operator_this.py
clouderizer/pkg/__init__.py
clouderizer/project.toml
clouderizer/setup.cfg
clouderizer/setup.py
clouderizer/template.yaml
clouderizer/templates/codebuild_buildspec.yaml
clouderizer/templates/codebuild_cloudformation_template.yaml
clouderizer/utils.py
clouderizer-0.0.18.dist-info/entry_points.txt
clouderizer-0.0.18.dist-info/WHEEL
clouderizer-0.0.18.dist-info/METADATA
clouderizer-0.0.18.dist-info/RECORD
